./.gitignore
./DEPLOYMENT_STRATEGY.md
./INSTALLATION.md
./INSTALLATION_SUMMARY.md
./LICENSE
./MCP_CONFIGURATION.md
./PKG-INFO
./Program.cs
./README.md
./ScreenshotMcpServer.csproj
./ScreenshotTool.cs
./Screenshot_mcp.sln
./copilot-instructions.md
./mcp.json
./package.json
./pyproject.toml
./screenshot_mcp_server.py
./tsconfig.json
./src/extension.ts
./src/index.ts
screenshot_mcp_server-1.0.0.dist-info/METADATA
screenshot_mcp_server-1.0.0.dist-info/WHEEL
screenshot_mcp_server-1.0.0.dist-info/entry_points.txt
screenshot_mcp_server-1.0.0.dist-info/licenses/LICENSE
screenshot_mcp_server-1.0.0.dist-info/RECORD
