Metadata-Version: 2.4
Name: screenshot-mcp-server
Version: 1.0.0
Summary: Windows Screenshot MCP Server - Capture screens with Print Screen simulation
Project-URL: Homepage, https://github.com/metamintbtc/desktop_screenshot_mcp_server
Project-URL: Documentation, https://github.com/metamintbtc/desktop_screenshot_mcp_server#readme
Project-URL: Repository, https://github.com/metamintbtc/desktop_screenshot_mcp_server.git
Project-URL: Issues, https://github.com/metamintbtc/desktop_screenshot_mcp_server/issues
Author-email: MetaMint <info@metamint.com>
License-Expression: MIT
License-File: LICENSE
Keywords: mcp,model-context-protocol,print-screen,screenshot,windows
Classifier: Development Status :: 5 - Production/Stable
Classifier: Intended Audience :: Developers
Classifier: License :: OSI Approved :: MIT License
Classifier: Operating System :: Microsoft :: Windows
Classifier: Programming Language :: Python :: 3
Classifier: Programming Language :: Python :: 3.8
Classifier: Programming Language :: Python :: 3.9
Classifier: Programming Language :: Python :: 3.10
Classifier: Programming Language :: Python :: 3.11
Classifier: Programming Language :: Python :: 3.12
Classifier: Topic :: Multimedia :: Graphics :: Capture :: Screen Capture
Classifier: Topic :: Software Development :: Libraries
Requires-Python: >=3.8
